jabbar/__init__.py
jabbar/bar.py
jabbar/version.py
test/__init__.py
test/test_basic.py
jabbar-0.0.15.dist-info/LICENSE
jabbar-0.0.15.dist-info/METADATA
jabbar-0.0.15.dist-info/WHEEL
jabbar-0.0.15.dist-info/top_level.txt
jabbar-0.0.15.dist-info/RECORD
