Metadata-Version: 2.1
Name: jabbar
Version: 0.0.15
Summary: Just Another Beautiful progress BAR
Home-page: https://github.com/yannikschaelte/jabbar
Author: Yannik Schaelte
Author-email: yannik.schaelte@gmail.com
Maintainer: Yannik Schaelte
Maintainer-email: yannik.schaelte@gmail.com
License: MIT
Download-URL: https://github.com/yannikschaelte/jabbar/releases
Project-URL: Bug Tracker, https://github.com/yannikschaelte/jabbar/issues
Project-URL: Source Code, https://github.com/yannikschaelte/jabbar
Project-URL: Documentation, https://github.com/yannikschaelte/jabbar
Keywords: Progress bar,Status bar,Jabberwocky
Platform: UNKNOWN
Classifier: Development Status :: 5 - Production/Stable
Classifier: License :: OSI Approved :: MIT License
Classifier: Operating System :: OS Independent
Classifier: Programming Language :: Python
Classifier: Programming Language :: Python :: 3.9
Classifier: Programming Language :: Python :: 3.8
Classifier: Programming Language :: Python :: 3.7
Classifier: Programming Language :: Python :: 3.6
Requires-Python: >=3.6
